{
    "type": "LaunchPad",
    "name": "Super large launch pad",
    "description": "Diamond shell allows it to store more items",
    "size": 4,
    "health":250 ,
	"size":4,
    "itemCapacity":600 ,
    "launchTime":800
	"update"	:true
    "hasItems"	:true
     "solid"	:true
	 "consumes": {
		"power":7.0 ,
}
    "requirements": [
	    {"item": "copper", "amount":500 } 
	    {"item": "石英", "amount":350 } 
		{"item": "lead", "amount":300 }
		{"item": "plastanium", "amount":125 }
		{"item": "钻石", "amount":20 }
		
	],
	"category": "effect",
	"research": "launch-pad-large"
}